raspsim/__init__.py
raspsim/__main__.py
raspsim/core.cpython-310-x86_64-linux-gnu.so
raspsim/core.cpython-311-x86_64-linux-gnu.so
raspsim/core.cpython-312-x86_64-linux-gnu.so
raspsim/core.cpython-37m-x86_64-linux-gnu.so
raspsim/core.cpython-38-x86_64-linux-gnu.so
raspsim/core.cpython-39-x86_64-linux-gnu.so
raspsim/core.pyi
raspsim/elf.py
raspsim/machinetypes.py
raspsim/raspsim.py
raspsim/utils.py
raspsim-0.1.0.7.1.dist-info/METADATA
raspsim-0.1.0.7.1.dist-info/WHEEL
raspsim-0.1.0.7.1.dist-info/top_level.txt
raspsim-0.1.0.7.1.dist-info/RECORD
