Metadata-Version: 2.1
Name: raspsim
Version: 0.1.0.7.1
Summary: Python bindings for the RaspSim C++ library, a cycle-accurate X86-64 simulator based on PTLSim.
Author-email: Janez Rotman <janez.rotman@tum.de>
Classifier: Programming Language :: Python :: 3.7
Classifier: Programming Language :: Python :: 3.8
Classifier: Programming Language :: Python :: 3.9
Classifier: Programming Language :: Python :: 3.10
Classifier: Programming Language :: Python :: 3.11
Classifier: Programming Language :: Python :: 3.12
Classifier: Operating System :: POSIX :: Linux
Classifier: License :: OSI Approved :: GNU General Public License v2 (GPLv2)
Requires-Dist: pyelftools
